Metadata-Version: 1.0
Name: AddOns
Version: 0.7
Summary: Dynamically extend other objects with AddOns (formerly ObjectRoles)
Home-page: http://pypi.python.org/pypi/AddOns
Author: Phillip J. Eby
Author-email: peak@eby-sarna.com
License: PSF or ZPL
Platform: UNKNOWN
